xy_pydev/BaseModuleData.py
xy_pydev/ModuleData.py
xy_pydev/PyDev.py
xy_pydev/Resource.py
xy_pydev/__init__.py
xy_pydev/data/.gitignore.template
xy_pydev/data/.xy-codehub-ci.yml.template
xy_pydev/data/MANIFEST.in.template
xy_pydev/data/VERSION.template
xy_pydev/data/pyproject.toml.template
xy_pydev/data/setup.py.template
xy_pydev/data/.vscode/settings.json.template
xy_pydev/data/execute/Main.py.template
xy_pydev/data/src/BaseModuleData.py.template
xy_pydev/data/src/Module.py.template
xy_pydev/data/src/ModuleData.py.template
xy_pydev/data/src/Resource.py.template
xy_pydev/execute/Main.py
xy_pydev/execute/__init__.py
xy_pydev-1.0.14.dist-info/licenses/LICENSE
xy_pydev-1.0.14.dist-info/METADATA
xy_pydev-1.0.14.dist-info/WHEEL
xy_pydev-1.0.14.dist-info/entry_points.txt
xy_pydev-1.0.14.dist-info/top_level.txt
xy_pydev-1.0.14.dist-info/RECORD
