Metadata-Version: 2.4
Name: xy_pydev
Version: 1.0.14
Summary: python开发模块
Author-email: 余洋 <yuyangit.0515@qq.com>
Classifier: Programming Language :: Python :: 3
Requires-Python: >=3.11.3
License-File: LICENSE
Requires-Dist: build
Requires-Dist: setuptools
Requires-Dist: twine
Requires-Dist: importlib_resources
Requires-Dist: xy_console
Requires-Dist: xy_string
Requires-Dist: xy_argparse
Requires-Dist: xy_file
Dynamic: license-file
